python_validate-0.0.2.dev0.dist-info/DESCRIPTION.rst
python_validate-0.0.2.dev0.dist-info/METADATA
python_validate-0.0.2.dev0.dist-info/RECORD
python_validate-0.0.2.dev0.dist-info/WHEEL
python_validate-0.0.2.dev0.dist-info/metadata.json
python_validate-0.0.2.dev0.dist-info/top_level.txt
validate/__init__.py
validate/check.py
validate/id_card.py
validate/utils.py
validate/vdate.py
