Metadata-Version: 2.0
Name: python-validate
Version: 0.0.2.dev0
Summary: python-validate表单验证
Home-page: https://github.com/ReanRen/Python-validate.git
Author: Rean
Author-email: rean.ren@qq.com
License: Public domain
Platform: any
